lettuce/__init__.py
lettuce/bin.py
lettuce/cacheprovider.py
lettuce/core.py
lettuce/decorators.py
lettuce/exceptions.py
lettuce/fs.py
lettuce/languages.py
lettuce/registry.py
lettuce/strings.py
lettuce/terminal.py
lettuce/terrain.py
lettuce/django/__init__.py
lettuce/django/apps.py
lettuce/django/server.py
lettuce/django/mail/__init__.py
lettuce/django/mail/backends.py
lettuce/django/management/__init__.py
lettuce/django/management/commands/__init__.py
lettuce/django/management/commands/harvest.py
lettuce/django/steps/__init__.py
lettuce/django/steps/mail.py
lettuce/django/steps/models.py
lettuce/django/tests/__init__.py
lettuce/django/tests/functional/__init__.py
lettuce/django/tests/functional/djangoapp.py
lettuce/django/tests/functional/steps.py
lettuce/django/tests/functional/terrain.py
lettuce/django/tests/functional/test_email.py
lettuce/django/tests/unit/__init__.py
lettuce/plugins/__init__.py
lettuce/plugins/autopdb.py
lettuce/plugins/colored_shell_output.py
lettuce/plugins/dots.py
lettuce/plugins/jsonreport_output.py
lettuce/plugins/non_verbose.py
lettuce/plugins/reporter.py
lettuce/plugins/scenario_names.py
lettuce/plugins/shell_output.py
lettuce/plugins/smtp_mail_queue.py
lettuce/plugins/subunit_output.py
lettuce/plugins/xunit_output.py
lettuce_Dtester-0.2.31.dist-info/LICENSE
lettuce_Dtester-0.2.31.dist-info/METADATA
lettuce_Dtester-0.2.31.dist-info/WHEEL
lettuce_Dtester-0.2.31.dist-info/entry_points.txt
lettuce_Dtester-0.2.31.dist-info/top_level.txt
lettuce_Dtester-0.2.31.dist-info/RECORD
