Metadata-Version: 2.1
Name: lettuce-Dtester
Version: 0.2.31
Summary: Behaviour Driven Development for python
Home-page: http://lettuce.it
Author: Gabriel Falcao
Author-email: gabriel@nacaolivre.org
License: UNKNOWN
Platform: UNKNOWN
License-File: LICENSE
Requires-Dist: sure
Requires-Dist: fuzzywuzzy
Requires-Dist: python-subunit
Requires-Dist: colorama
